mirror_git_to_s3.py
mirror_git_to_s3-0.0.24.dist-info/METADATA
mirror_git_to_s3-0.0.24.dist-info/WHEEL
mirror_git_to_s3-0.0.24.dist-info/entry_points.txt
mirror_git_to_s3-0.0.24.dist-info/licenses/LICENSE
mirror_git_to_s3-0.0.24.dist-info/RECORD
