Metadata-Version: 2.3
Name: mirror-git-to-s3
Version: 0.0.24
Summary: Python functions and CLI to mirror git repositories available on HTTP(S) to S3
Project-URL: Homepage, https://github.com/uktrade/mirror-git-to-s3
Project-URL: Bug Tracker, https://github.com/uktrade/mirror-git-to-s3/issues
Author-email: Department for International Trade <sre@digital.trade.gov.uk>
Classifier: License :: OSI Approved :: MIT License
Classifier: Operating System :: OS Independent
Classifier: Programming Language :: Python :: 3
Classifier: Topic :: Software Development :: Version Control :: Git
Requires-Python: >=3.8
Requires-Dist: boto3>=1.17.112
Requires-Dist: click>=8.1.3
Requires-Dist: httpx>=0.23.1
Requires-Dist: tqdm>=4.65.0
Provides-Extra: dev
Requires-Dist: pytest; extra == 'dev'
Requires-Dist: pytest-cov; extra == 'dev'
